tinyNLP/__init__.py
tinyNLP/tests.py
tinyNLP/tinyNLP.py
tinyNLP-0.1.dist-info/DESCRIPTION.rst
tinyNLP-0.1.dist-info/METADATA
tinyNLP-0.1.dist-info/RECORD
tinyNLP-0.1.dist-info/WHEEL
tinyNLP-0.1.dist-info/metadata.json
tinyNLP-0.1.dist-info/top_level.txt
