Metadata-Version: 2.0
Name: tinyNLP
Version: 0.1
Summary: Super-minimal NLP package
Home-page: http://github.com/crgirard/tinyNLP
Author: Corey Girard
Author-email: corey.r.girard@gmail.com
License: MIT
Platform: UNKNOWN
